snakemake_storage_plugin_rucio/__init__.py
snakemake_storage_plugin_rucio-0.4.1.dist-info/LICENSE
snakemake_storage_plugin_rucio-0.4.1.dist-info/METADATA
snakemake_storage_plugin_rucio-0.4.1.dist-info/WHEEL
snakemake_storage_plugin_rucio-0.4.1.dist-info/RECORD
